{
  "version": 1,
  "isRoot": true,
  "tools": {
    "dotnet-outdated-tool": {
      "version": "4.6.8",
      "commands": [
        "dotnet-outdated"
      ],
      "rollForward": false
    },
    "dotnet-ef": {
      "version": "9.0.3",
      "commands": [
        "dotnet-ef"
      ],
      "rollForward": false
    },
    "dotnet-format": {
      "version": "5.1.250801",
      "commands": [
        "dotnet-format"
      ],
      "rollForward": false
    },
    "aspirate": {
      "version": "9.1.0",
      "commands": [
        "aspirate"
      ],
      "rollForward": false
    }
  }
}